traduki/__init__.py
traduki/config.py
traduki/helpers.py
traduki/sqla.py
traduki-1.3.3.dist-info/LICENSE.txt
traduki-1.3.3.dist-info/METADATA
traduki-1.3.3.dist-info/WHEEL
traduki-1.3.3.dist-info/top_level.txt
traduki-1.3.3.dist-info/RECORD
