Metadata-Version: 2.1
Name: traduki
Version: 1.3.3
Summary: SQLAlchemy internationalisation
Home-page: https://github.com/paylogic/traduki
Author: Paylogic International
Author-email: developers@paylogic.com
License: MIT
Keywords: sqlalchemy i18n internationalisation
Platform: UNKNOWN
Classifier: Development Status :: 5 - Production/Stable
Classifier: Intended Audience :: Developers
Classifier: Programming Language :: Python :: 2
Classifier: Programming Language :: Python :: 2.7
Classifier: Programming Language :: Python :: 3
Classifier: Programming Language :: Python :: 3.5
Classifier: Programming Language :: Python :: 3.6
Classifier: Programming Language :: Python :: 3.7
Classifier: Programming Language :: Python :: 3.8
License-File: LICENSE.txt
Requires-Dist: SQLAlchemy
Requires-Dist: six (>=1.9.0)
